dvf/__init__.py
dvf/conditions.py
dvf/constant.py
dvf/dvf.py
dvf/format.py
dvf/magic.py
dvf/obj_node.py
dvf/utils.py
dvf-0.1.2.dist-info/LICENSE
dvf-0.1.2.dist-info/METADATA
dvf-0.1.2.dist-info/WHEEL
dvf-0.1.2.dist-info/top_level.txt
dvf-0.1.2.dist-info/RECORD
