Metadata-Version: 2.1
Name: dvf
Version: 0.1.2
Summary: A dual vector foil (二向箔) that squashes any Python objects into your console.
Home-page: https://github.com/liwt31/dual_vector_foil
Author: liwt31
Author-email: liwt31@163.com
License: MIT
Platform: UNKNOWN
Classifier: Development Status :: 3 - Alpha
Classifier: Intended Audience :: Developers
Classifier: License :: OSI Approved :: MIT License
Classifier: Programming Language :: Python :: 3
Classifier: Programming Language :: Python :: 3.6
Classifier: Programming Language :: Python :: 3.7
Classifier: Programming Language :: Python
Classifier: Topic :: Software Development
Requires-Dist: print-tree2
Requires-Dist: colorama
Requires-Dist: termcolor
